AlignmentReporter/Vizualisation.py
AlignmentReporter/__init__.py
AlignmentReporter/UI/AlignmentTool.ico
AlignmentReporter/UI/__init__.py
AlignmentReporter/UI/Qt/AlignmentReporterRessources.py
AlignmentReporter/UI/Qt/AlignmentReporterRessources.qrc
AlignmentReporter/UI/Qt/compileRessources.bat
AlignmentReporter/UI/Qt/compileRessources.sh
AlignmentReporter/UI/Qt/imageSettings.ui
AlignmentReporter/UI/Qt/mainWindow.ui
AlignmentReporter/UI/Qt/style.css
AlignmentReporter/UI/Qt/icons/arrow_down.png
AlignmentReporter/UI/Qt/icons/arrow_left.png
AlignmentReporter/UI/Qt/icons/arrow_right.png
AlignmentReporter/UI/Qt/icons/arrow_up.png
AlignmentReporter/UI/Qt/icons/loading.png
AlignmentReporter/UI/py/__init__.py
AlignmentReporter/UI/py/classutils.py
AlignmentReporter/UI/py/default_parameters.py
AlignmentReporter/UI/py/funcutils.py
AlignmentReporter/UI/py/typed_dict.py
AlignmentReporter/data/Celtaidd.json
AlignmentReporter/data/Celtaidd.pkl
AlignmentReporter/data/TMP.pkl
AlignmentReporter/data/Volac.json
AlignmentReporter/data/Volac.pkl
AlignmentReporter/out/celtaidd_s_murder_hobos.png
AlignmentReporter/out/volac_s_stupid_freaks.jpg
AlignmentReporter/out/volac_s_stupid_freaks.png
AlignR-2.0.5.dist-info/LICENSE
AlignR-2.0.5.dist-info/METADATA
AlignR-2.0.5.dist-info/WHEEL
AlignR-2.0.5.dist-info/entry_points.txt
AlignR-2.0.5.dist-info/top_level.txt
AlignR-2.0.5.dist-info/RECORD
