Metadata-Version: 2.1
Name: AlignR
Version: 2.0.5
Summary: Simple Tool to track the alignments of your players
Home-page: https://github.com/JulienAlardot/AlignmentReporter
Author: Julien Alardot
Author-email: "Julien Alardot" <cschultz@example.com>
License: GPlv3
Project-URL: Bug Tracker, https://github.com/JulienAlardot/AlignmentReporter/issues
Platform: UNKNOWN
Classifier: Programming Language :: Python
Classifier: Natural Language :: English
Classifier: Operating System :: OS Independent
Classifier: Programming Language :: Python :: 3.8
Classifier: Topic :: Games/Entertainment :: Role-Playing
Requires-Python: >=3.8
Requires-Dist: setuptools (>=40.8.0)
Requires-Dist: PySide2 (>=5.14)
Requires-Dist: matplotlib (<=3.3)
Requires-Dist: numpy (<=1.20)
Requires-Dist: pyparsing
Requires-Dist: Cython (>=0.29)
Requires-Dist: pandas (>=1.2)
Requires-Dist: scipy (>=1.6)
